{
  "asset_name": "coa_districts_water.lib",
  "asset_id": "27bf6221c374d6ca2236",
  "run_group_id": "c1eb20ee50203635e5a7",
  "active": true,
  "tasks": [
    {
      "task_id": "4bfe77b521c997a6304c",
      "asset_id": "27bf6221c374d6ca2236",
      "seq_number": 0,
      "description": null,
      "type": "table_copy",
      "active": true,
      "source": {
        "asset": "coa_districts_water.wh"
      },
      "target": {
        "asset": "coa_districts_water.lib"
      },
      "configuration": null
    }
  ]
}