{
  "asset_name": "inspections.lib",
  "asset_id": "55afc075ba5b5c552625",
  "run_group_id": "c1eb20ee50203635e5a7",
  "active": true,
  "tasks": [
    {
      "task_id": "053489b15f5c18eaa593",
      "asset_id": "55afc075ba5b5c552625",
      "seq_number": 0,
      "description": null,
      "type": "table_copy",
      "active": true,
      "source": {
        "asset": "inspections.acc"
      },
      "target": {
        "asset": "inspections.lib"
      },
      "configuration": null
    }
  ]
}